{
  "meta": {
    "generated_at": "2026-02-08T17:54:01.047935",
    "main_index": 6.94,
    "status": "ELEVATED",
    "active_scan": true,
    "next_update": "2026-02-08T18:00:00",
    "version": "2.0.0"
  },
  "countries": {
    "Armenia": {
      "index": 4.19,
      "raw_score": 14.75,
      "events": [
        {
          "title": "A matter of national conscience: The sentencing in Baku",
          "translated_title": "A matter of national conscience: The sentencing in Baku",
          "link": "https://armenianweekly.com/2026/02/07/a-matter-of-national-conscience-the-sentencing-in-baku/",
          "date": "Sat, 07 Feb 2026 15:14:38 +0000",
          "category": "political crisis",
          "confidence": 0.9458833336830139,
          "weight": 5.6753000020980835,
          "ai_model": "XLM-RoBERTa-Large-XNLI",
          "ai_confidence_score": "94.6%",
          "detected_lang": "en",
          "is_translated": false,
          "country": "Armenia"
        },
        {
          "title": "Western Azerbaijan: Armenian court decision risks derailing Baku-Yerevan normalisation - AzerNews",
          "translated_title": "Western Azerbaijan: Armenian court decision risks derailing Baku-Yerevan normalisation - AzerNews",
          "link": "https://news.google.com/rss/articles/CBMiVEFVX3lxTE1jR0NkX3dGUXFUSmZnbW5EeGgtemN3WnpkTm51YnBKZXdwQW9rZmJPOVJPNTRfT1hmNW50QlpmbUxQSXRXR3k2Tnc0Q210aTVCT1FVeA?oc=5",
          "date": "Sun, 08 Feb 2026 14:55:20 GMT",
          "category": "political crisis",
          "confidence": 0.7587093114852905,
          "weight": 4.552255868911743,
          "ai_model": "XLM-RoBERTa-Large-XNLI",
          "ai_confidence_score": "75.9%",
          "detected_lang": "en",
          "is_translated": false,
          "country": "Armenia"
        },
        {
          "title": "ANCA demands records on Dr. Oz’s anti-Armenian video",
          "translated_title": "ANCA demands records on Dr. Oz’s anti-Armenian video",
          "link": "https://armenianweekly.com/2026/02/06/anca-demands-records-on-dr-ozs-anti-armenian-video/",
          "date": "Fri, 06 Feb 2026 19:45:28 +0000",
          "category": "political crisis",
          "confidence": 0.7542021870613098,
          "weight": 4.525213122367859,
          "ai_model": "XLM-RoBERTa-Large-XNLI",
          "ai_confidence_score": "75.4%",
          "detected_lang": "local",
          "is_translated": true,
          "country": "Armenia",
          "translation_engine": "Google Neural MT"
        },
        {
          "title": "Armenia’s security architecture in a changing balance of power: The role of India and France, risks and prospects",
          "translated_title": null,
          "link": "https://armenianweekly.com/2026/02/07/armenias-security-architecture-in-a-changing-balance-of-power-the-role-of-india-and-france-risks-and-prospects/",
          "date": "Sat, 07 Feb 2026 18:47:51 +0000",
          "category": "peaceful diplomacy",
          "confidence": 0.2281789928674698,
          "weight": 0.0,
          "ai_model": "XLM-RoBERTa-Large-XNLI",
          "ai_confidence_score": "22.8%",
          "detected_lang": "local",
          "is_translated": false,
          "country": "Armenia"
        },
        {
          "title": "Book review: ‘Life Within the Armenian Community of Aleppo’",
          "translated_title": null,
          "link": "https://armenianweekly.com/2026/02/07/book-review-life-within-the-armenian-community-of-aleppo/",
          "date": "Sat, 07 Feb 2026 15:01:24 +0000",
          "category": "humanitarian crisis",
          "confidence": 0.24471500515937805,
          "weight": 0.0,
          "ai_model": "XLM-RoBERTa-Large-XNLI",
          "ai_confidence_score": "24.5%",
          "detected_lang": "local",
          "is_translated": false,
          "country": "Armenia"
        },
        {
          "title": "Remembering Adiss Harmandian through his daughter’s eyes",
          "translated_title": null,
          "link": "https://armenianweekly.com/2026/02/07/remembering-adiss-harmandian-through-his-daughters-eyes/",
          "date": "Sat, 07 Feb 2026 14:58:57 +0000",
          "category": "violent protest",
          "confidence": 0.18746565282344818,
          "weight": 0.0,
          "ai_model": "XLM-RoBERTa-Large-XNLI",
          "ai_confidence_score": "18.7%",
          "detected_lang": "local",
          "is_translated": false,
          "country": "Armenia"
        },
        {
          "title": "ANCA calls on Vice President Vance to secure Azerbaijan’s release of Armenian hostages during South Caucasus visits",
          "translated_title": null,
          "link": "https://armenianweekly.com/2026/02/06/anca-calls-on-vice-president-vance-to-secure-azerbaijans-release-of-armenian-hostages-during-south-caucasus-visits/",
          "date": "Fri, 06 Feb 2026 23:14:49 +0000",
          "category": "violent protest",
          "confidence": 0.19415509700775146,
          "weight": 0.0,
          "ai_model": "XLM-RoBERTa-Large-XNLI",
          "ai_confidence_score": "19.4%",
          "detected_lang": "local",
          "is_translated": false,
          "country": "Armenia"
        },
        {
          "title": "Nikol Aghababyan’s return to the “small corner of the great world”",
          "translated_title": null,
          "link": "https://armenianweekly.com/2026/02/06/nikol-aghababyans-return-to-the-small-corner-of-the-great-world/",
          "date": "Fri, 06 Feb 2026 22:15:49 +0000",
          "category": "neutral news",
          "confidence": 0.2467067837715149,
          "weight": 0.0,
          "ai_model": "XLM-RoBERTa-Large-XNLI",
          "ai_confidence_score": "24.7%",
          "detected_lang": "local",
          "is_translated": false,
          "country": "Armenia"
        },
        {
          "title": "‘The Melody of Armenia’: How a lost silent film was restored and given a new voice",
          "translated_title": null,
          "link": "https://armenianweekly.com/2026/02/06/the-melody-of-armenia-how-a-lost-silent-film-was-restored-and-given-a-new-voice/",
          "date": "Fri, 06 Feb 2026 19:58:48 +0000",
          "category": "terrorist act",
          "confidence": 0.21534131467342377,
          "weight": 0.0,
          "ai_model": "XLM-RoBERTa-Large-XNLI",
          "ai_confidence_score": "21.5%",
          "detected_lang": "local",
          "is_translated": false,
          "country": "Armenia"
        },
        {
          "title": "AYF-YOARF Central Council convenes for 2026 planning weekend",
          "translated_title": null,
          "link": "https://armenianweekly.com/2026/02/06/ayf-yoarf-central-council-convenes-for-2026-planning-weekend/",
          "date": "Fri, 06 Feb 2026 19:49:50 +0000",
          "category": "neutral news",
          "confidence": 0.30450907349586487,
          "weight": 0.0,
          "ai_model": "XLM-RoBERTa-Large-XNLI",
          "ai_confidence_score": "30.5%",
          "detected_lang": "en",
          "is_translated": false,
          "country": "Armenia"
        },
        {
          "title": "Catholicos Aram I and EEAS Delegation Meet in Antelias",
          "translated_title": null,
          "link": "https://hetq.am/en/article/179618",
          "date": "Fri, 06 Feb 2026 18:22:00 +0400",
          "category": "neutral news",
          "confidence": 0.2817237079143524,
          "weight": 0.0,
          "ai_model": "XLM-RoBERTa-Large-XNLI",
          "ai_confidence_score": "28.2%",
          "detected_lang": "en",
          "is_translated": false,
          "country": "Armenia"
        },
        {
          "title": "Once Washington's Closest Caucasus Partner, Georgia To Watch Vance Visit From The Outside - rferl.org",
          "translated_title": null,
          "link": "https://news.google.com/rss/articles/CBMilwFBVV95cUxOeWtzMzlzVFNPR2h6dTNzeTlTY1p0eXJmZXMxb1pxWlFua2dkdmU2bzVrWEdMSFVvMGRDbVpicG5SUWJwZVFHNVRONHhFNmcyekVraWt3UEtsVzdJS2V4VEhUOGdGb18wck4tMjNfTTdIcVFxOEU3ZTFrVzNMUGxIOWh3akVuSkcxdjlucTNIcU1WVVRIN3lN0gGaAUFVX3lxTFBGSGt6LTR3N3Y0SFYzTi1kekU5TlljOGlsZ2t3ZUxFSkJoMkxwUG9YSVpGaTl2aERHbksxY015TWZnZzUtUUhLUVo3dWxYUDRMN1ZRV1NyeDZlZl8yMXhzLVM4cE1aWkNFc29HdkxhWU0xemlKNXNWNFVLdjdaYk56ZGpaMVhfSFFNV3p5Rzd0ZTg4UUd5em01WlE?oc=5",
          "date": "Sun, 08 Feb 2026 15:53:12 GMT",
          "category": "neutral news",
          "confidence": 0.298932820558548,
          "weight": 0.0,
          "ai_model": "XLM-RoBERTa-Large-XNLI",
          "ai_confidence_score": "29.9%",
          "detected_lang": "en",
          "is_translated": false,
          "country": "Armenia"
        },
        {
          "title": "Armenia: A future colored by hope - San Diego Union-Tribune",
          "translated_title": null,
          "link": "https://news.google.com/rss/articles/CBMiiAFBVV95cUxOOXpGcUgyM2tUMjR5SWhnZzhDMWtBWHIwcXA3Wkg5YU10TkI1YkNQOHFPdm02cE1OUE9zdDFGak9va3pUeEVHX1J2Q2FZNFpZZ3ZXOTAweWFEcXM2OThkS2p4V3dGQ1h0YjMyUTd0dFFseXVXeXRjdmZSb21uS1Bydmt1WmhxVl9y?oc=5",
          "date": "Sun, 08 Feb 2026 14:01:20 GMT",
          "category": "neutral news",
          "confidence": 0.4827086329460144,
          "weight": 0.0,
          "ai_model": "XLM-RoBERTa-Large-XNLI",
          "ai_confidence_score": "48.3%",
          "detected_lang": "en",
          "is_translated": false,
          "country": "Armenia"
        },
        {
          "title": "Armenia’s security architecture in a changing balance of power: The role of India and France, risks and prospects - The Armenian Weekly",
          "translated_title": null,
          "link": "https://news.google.com/rss/articles/CBMi4wFBVV95cUxNMmhTdTkzZHhyNS1uY2JiVGJSOF9DbU4tRFM2YjNobHItOURSc2YwdFRoUjNLaE1yQ0dNOWxaTFhvdi1KdHBzekxfY2g1em9ka3FqYmNiUHRZYTVrcThnZXlVbnZwMjNzazE4WVNQS1A4aUpqaGxaSGVGaTVoeEdtZmtmZkJOMUhoYV9vdXZlVkd4TzctWWRyVi1GTGs2ZzRlQmJpbVU3RVRUd2k1LU8wN0xTQndYVzBKT2JULVRkSVFuR1ktVHRxRXpNOUFrdjFycjVJcXJxV2JtamN4RFdoN3A0dw?oc=5",
          "date": "Sat, 07 Feb 2026 18:52:38 GMT",
          "category": "peaceful diplomacy",
          "confidence": 0.36827901005744934,
          "weight": 0.0,
          "ai_model": "XLM-RoBERTa-Large-XNLI",
          "ai_confidence_score": "36.8%",
          "detected_lang": "local",
          "is_translated": false,
          "country": "Armenia"
        },
        {
          "title": "Vance Should Bypass Azerbaijan After Its ‘Kangaroo Court’ Sentencings of Armenians - Middle East Forum",
          "translated_title": null,
          "link": "https://news.google.com/rss/articles/CBMiuAFBVV95cUxQNEwyZzVyQmN5REs5cjgtc0tNai1ReGxYM2lqdzJYYnVuY2syMk8zLUdTS29wQU5uOGlXc3R1Y3RVMjd5U1hobEt6cWlSNWM4YVdNNjd0VWpvZFVNWG5PbEtSZTAwTEtJelFzU2hpY3JOaHRJeXMwc1BPTkhqYmFrXzY2WWN4UWFRVkZwNFVJYTRiM2dTamxPZmN2cDJZRF9zRVdnTDRZemVMY2Y1bFRobmowNlVoTTFp?oc=5",
          "date": "Sun, 08 Feb 2026 11:01:25 GMT",
          "category": "political crisis",
          "confidence": 0.3947545886039734,
          "weight": 0.0,
          "ai_model": "XLM-RoBERTa-Large-XNLI",
          "ai_confidence_score": "39.5%",
          "detected_lang": "local",
          "is_translated": false,
          "country": "Armenia"
        }
      ]
    },
    "Georgia": {
      "index": 4.35,
      "raw_score": 16.44,
      "events": [
        {
          "title": "64 წლის კაცი განზრახ მკვლელობის მცდელობის ბრალდებით დააკავეს – შსს",
          "translated_title": "A 64-year-old man was arrested on charges of attempted murder - Ministry of Internal Affairs",
          "link": "https://netgazeti.ge/news/797911/",
          "date": "Sat, 07 Feb 2026 12:29:56 +0000",
          "category": "terrorist act",
          "confidence": 0.9722194671630859,
          "weight": 8.749975204467773,
          "ai_model": "XLM-RoBERTa-Large-XNLI",
          "ai_confidence_score": "97.2%",
          "detected_lang": "local",
          "is_translated": true,
          "country": "Georgia",
          "translation_engine": "Google Neural MT"
        },
        {
          "title": "პირადი ცხოვრების ამსახველი ინფორმაციით შანტაჟის გამო ერთი პირი დააკავეს",
          "translated_title": "One person was arrested for blackmailing him with personal information",
          "link": "https://netgazeti.ge/news/797948/",
          "date": "Sun, 08 Feb 2026 10:25:21 +0000",
          "category": "violent protest",
          "confidence": 0.698029637336731,
          "weight": 4.886207461357117,
          "ai_model": "XLM-RoBERTa-Large-XNLI",
          "ai_confidence_score": "69.8%",
          "detected_lang": "local",
          "is_translated": true,
          "country": "Georgia",
          "translation_engine": "Google Neural MT"
        },
        {
          "title": "Meydan TV case in Azerbaijan: journalists barred from presenting motions at court",
          "translated_title": "Meydan TV case in Azerbaijan: journalists barred from presenting motions at court",
          "link": "https://jam-news.net/the-meydan-tv-trial-in-azerbaijan-journalists-barred-from-presenting-motions-at-court/",
          "date": "Sun, 08 Feb 2026 09:15:58 +0000",
          "category": "political crisis",
          "confidence": 0.6142447590827942,
          "weight": 3.685468554496765,
          "ai_model": "XLM-RoBERTa-Large-XNLI",
          "ai_confidence_score": "61.4%",
          "detected_lang": "en",
          "is_translated": false,
          "country": "Georgia"
        },
        {
          "title": "PhotoEssay | My Once-Rebellious Municipality",
          "translated_title": null,
          "link": "https://civil.ge/archives/719501",
          "date": "Sun, 08 Feb 2026 13:12:17 +0000",
          "category": "violent protest",
          "confidence": 0.32715657353401184,
          "weight": 0.0,
          "ai_model": "XLM-RoBERTa-Large-XNLI",
          "ai_confidence_score": "32.7%",
          "detected_lang": "en",
          "is_translated": false,
          "country": "Georgia"
        },
        {
          "title": "Key Georgian pro-government media outlet Imedi to be sold",
          "translated_title": null,
          "link": "https://oc-media.org/key-georgian-pro-government-media-outlet-imedi-to-be-sold/",
          "date": "Sat, 07 Feb 2026 12:45:34 +0000",
          "category": "neutral news",
          "confidence": 0.21300868690013885,
          "weight": 0.0,
          "ai_model": "XLM-RoBERTa-Large-XNLI",
          "ai_confidence_score": "21.3%",
          "detected_lang": "en",
          "is_translated": false,
          "country": "Georgia"
        },
        {
          "title": "დასასრულის დასასრულია – ნინო კასრაძის სიტყვა კულტურის სფეროში რეპრესიებზე",
          "translated_title": null,
          "link": "https://netgazeti.ge/art/797959/",
          "date": "Sun, 08 Feb 2026 15:33:16 +0000",
          "category": "peaceful diplomacy",
          "confidence": 0.19826899468898773,
          "weight": 0.0,
          "ai_model": "XLM-RoBERTa-Large-XNLI",
          "ai_confidence_score": "19.8%",
          "detected_lang": "local",
          "is_translated": false,
          "country": "Georgia"
        },
        {
          "title": "“ახალი საზოგადოებრივი შეთანხმება – საქართველოს გულისთვის”- ფორუმი თბილისში",
          "translated_title": null,
          "link": "https://netgazeti.ge/news/797957/",
          "date": "Sun, 08 Feb 2026 15:00:14 +0000",
          "category": "neutral news",
          "confidence": 0.2737124264240265,
          "weight": 0.0,
          "ai_model": "XLM-RoBERTa-Large-XNLI",
          "ai_confidence_score": "27.4%",
          "detected_lang": "local",
          "is_translated": false,
          "country": "Georgia"
        },
        {
          "title": "როგორ საქართველოში მინდა ცხოვრება? – მასწავლებელი დათია ბადალაშვილი",
          "translated_title": null,
          "link": "https://netgazeti.ge/opinion/797951/",
          "date": "Sun, 08 Feb 2026 12:53:40 +0000",
          "category": "neutral news",
          "confidence": 0.33491331338882446,
          "weight": 0.0,
          "ai_model": "XLM-RoBERTa-Large-XNLI",
          "ai_confidence_score": "33.5%",
          "detected_lang": "local",
          "is_translated": false,
          "country": "Georgia"
        },
        {
          "title": "სამუშია არ ადასტურებს, რომ დატოვა თსუ-ის რექტორის თანამდებობა",
          "translated_title": null,
          "link": "https://netgazeti.ge/news/797927/",
          "date": "Sat, 07 Feb 2026 16:51:43 +0000",
          "category": "violent protest",
          "confidence": 0.23330067098140717,
          "weight": 0.0,
          "ai_model": "XLM-RoBERTa-Large-XNLI",
          "ai_confidence_score": "23.3%",
          "detected_lang": "local",
          "is_translated": false,
          "country": "Georgia"
        },
        {
          "title": "პენიტენციურ უარყოფს ინფორმაციას, რომ გლდანის ციხის პატიმრებს მობილურის სარგებლობის უფლება შეეზღუდათ",
          "translated_title": null,
          "link": "https://netgazeti.ge/news/797919/",
          "date": "Sat, 07 Feb 2026 14:29:00 +0000",
          "category": "neutral news",
          "confidence": 0.476364403963089,
          "weight": 0.0,
          "ai_model": "XLM-RoBERTa-Large-XNLI",
          "ai_confidence_score": "47.6%",
          "detected_lang": "local",
          "is_translated": false,
          "country": "Georgia"
        },
        {
          "title": "“უზღუდავდა განათლების მიღების და მუშაობისა უფლებას” – ცოლის მკვლელობის ბრალდებით კაცი დააკავეს",
          "translated_title": null,
          "link": "https://netgazeti.ge/news/797916/",
          "date": "Sat, 07 Feb 2026 13:53:31 +0000",
          "category": "terrorist act",
          "confidence": 0.36366522312164307,
          "weight": 0.0,
          "ai_model": "XLM-RoBERTa-Large-XNLI",
          "ai_confidence_score": "36.4%",
          "detected_lang": "local",
          "is_translated": false,
          "country": "Georgia"
        },
        {
          "title": "კობახიძის პასუხი კითხვაზე, გადაიხედება თუ არა თსუ-სა და სტუ-ის გაერთიანების გადაწყვეტილება",
          "translated_title": null,
          "link": "https://netgazeti.ge/news/797907/",
          "date": "Sat, 07 Feb 2026 10:56:37 +0000",
          "category": "neutral news",
          "confidence": 0.21890227496623993,
          "weight": 0.0,
          "ai_model": "XLM-RoBERTa-Large-XNLI",
          "ai_confidence_score": "21.9%",
          "detected_lang": "local",
          "is_translated": false,
          "country": "Georgia"
        },
        {
          "title": "19 და 24 წლის ბიჭები სწრაფი ჩარიცხვის აპარატის გაქურდვისთვის დააკავეს – შსს",
          "translated_title": null,
          "link": "https://netgazeti.ge/news/797899/",
          "date": "Sat, 07 Feb 2026 08:17:25 +0000",
          "category": "terrorist act",
          "confidence": 0.39673107862472534,
          "weight": 0.0,
          "ai_model": "XLM-RoBERTa-Large-XNLI",
          "ai_confidence_score": "39.7%",
          "detected_lang": "local",
          "is_translated": false,
          "country": "Georgia"
        },
        {
          "title": "In Abkhazia, a local Georgian-Abkhaz war veteran’s view on the Lata tragedy was called blasphemous",
          "translated_title": null,
          "link": "https://jam-news.net/georgian-abkhaz-war-veterans-view-yaganov-on-the-lata-tragedy/",
          "date": "Sat, 07 Feb 2026 13:20:25 +0000",
          "category": "military conflict",
          "confidence": 0.38662633299827576,
          "weight": 0.0,
          "ai_model": "XLM-RoBERTa-Large-XNLI",
          "ai_confidence_score": "38.7%",
          "detected_lang": "local",
          "is_translated": false,
          "country": "Georgia"
        },
        {
          "title": "თუკი მართლა დიადი რეფორმა უნდათ, მაშინ ჩაერთოს ყველა – პროფესორი უნივერსიტეტების გაერთიანებზე",
          "translated_title": null,
          "link": "https://netgazeti.ge/news/797931/",
          "date": "Sat, 07 Feb 2026 19:00:32 +0000",
          "category": "peaceful diplomacy",
          "confidence": 0.4388442933559418,
          "weight": -0.8776885867118835,
          "ai_model": "XLM-RoBERTa-Large-XNLI",
          "ai_confidence_score": "43.9%",
          "detected_lang": "local",
          "is_translated": false,
          "country": "Georgia"
        }
      ]
    },
    "Greece": {
      "index": 1.5,
      "raw_score": 1.69,
      "events": [
        {
          "title": "Πλεύρης για τους ακτιβιστές που ζήτησαν να δουν παιδιά από το ναυάγιο στη Χίο: Αρκετά με τις προκλήσεις των επαγγελματιών ανθρωπιστών",
          "translated_title": null,
          "link": "https://www.protothema.gr/politics/article/1770540/pleuris-aktivistes-paidia-nauagio-sti-hio-arketa-me-tis-prokliseis-ton-epaggelmation-anthropiston/?utm_source=rss",
          "date": "Sun, 08 Feb 2026 17:27:00 +0200",
          "category": "humanitarian crisis",
          "confidence": 0.9366909265518188,
          "weight": 2.8100727796554565,
          "ai_model": "XLM-RoBERTa-Large-XNLI",
          "ai_confidence_score": "93.7%",
          "detected_lang": "local",
          "is_translated": false,
          "country": "Greece"
        },
        {
          "title": "Τσιτσιπάς και Σακελλαρίδης πήραν τη νίκη στο διπλό: Προβάδισμα της Ελλάδας με 2-1 κόντρα στο Μεξικό",
          "translated_title": null,
          "link": "https://www.protothema.gr/sports/article/1770556/tsitsipas-kai-sakellaridis-piran-ti-niki-sto-diplo-provadisma-tis-elladas-me-2-1-kodra-sto-mexiko/?utm_source=rss",
          "date": "Sun, 08 Feb 2026 19:29:00 +0200",
          "category": "violent protest",
          "confidence": 0.34183454513549805,
          "weight": 0.0,
          "ai_model": "XLM-RoBERTa-Large-XNLI",
          "ai_confidence_score": "34.2%",
          "detected_lang": "local",
          "is_translated": false,
          "country": "Greece"
        },
        {
          "title": "Φωτιά τώρα σε κτίριο στον Βόλο, δείτε φωτογραφίες",
          "translated_title": null,
          "link": "https://www.protothema.gr/greece/article/1770555/fotia-tora-se-ktirio-ston-volo-deite-fotografies/?utm_source=rss",
          "date": "Sun, 08 Feb 2026 19:23:00 +0200",
          "category": "violent protest",
          "confidence": 0.3366756737232208,
          "weight": 0.0,
          "ai_model": "XLM-RoBERTa-Large-XNLI",
          "ai_confidence_score": "33.7%",
          "detected_lang": "local",
          "is_translated": false,
          "country": "Greece"
        },
        {
          "title": "Συνελήφθησαν τρία άτομα στα Τρίκαλα για πώληση τσιγάρων σε ανήλικους",
          "translated_title": null,
          "link": "https://www.protothema.gr/greece/article/1770554/sunelifthisan-treis-peripterades-sta-trikala-gia-polisi-tsigaron-se-anilikous/?utm_source=rss",
          "date": "Sun, 08 Feb 2026 19:10:00 +0200",
          "category": "military conflict",
          "confidence": 0.16832751035690308,
          "weight": 0.0,
          "ai_model": "XLM-RoBERTa-Large-XNLI",
          "ai_confidence_score": "16.8%",
          "detected_lang": "local",
          "is_translated": false,
          "country": "Greece"
        },
        {
          "title": "Νίκολιτς: «Ο κόσμος είναι ο MVP»",
          "translated_title": null,
          "link": "https://www.protothema.gr/sports/article/1770553/nikolits-o-kosmos-einai-o-mvp/?utm_source=rss",
          "date": "Sun, 08 Feb 2026 18:45:00 +0200",
          "category": "neutral news",
          "confidence": 0.3146790564060211,
          "weight": 0.0,
          "ai_model": "XLM-RoBERTa-Large-XNLI",
          "ai_confidence_score": "31.5%",
          "detected_lang": "local",
          "is_translated": false,
          "country": "Greece"
        },
        {
          "title": "Γυναίκα είναι ο «άνθρωπος-σκιά» πίσω από τον σμήναρχο που κατασκόπευε υπέρ της Κίνας",
          "translated_title": null,
          "link": "https://www.protothema.gr/greece/article/1770552/gunaika-einai-o-anthropos-skia-piso-apo-ton-sminarho-pou-kataskopeue-uper-tis-kinas/?utm_source=rss",
          "date": "Sun, 08 Feb 2026 18:33:00 +0200",
          "category": "terrorist act",
          "confidence": 0.4854682385921478,
          "weight": 0.0,
          "ai_model": "XLM-RoBERTa-Large-XNLI",
          "ai_confidence_score": "48.5%",
          "detected_lang": "local",
          "is_translated": false,
          "country": "Greece"
        },
        {
          "title": "Κατάρρευση κτιρίου στον Λίβανο: Τρεις άνθρωποι βγήκαν ζωντανοί από τα συντρίμμια",
          "translated_title": null,
          "link": "https://www.protothema.gr/world/article/1770551/katarreusi-ktiriou-ston-livano-treis-anthropoi-vgikan-zodanoi-apo-ta-sudrimmia/?utm_source=rss",
          "date": "Sun, 08 Feb 2026 18:21:54 +0200",
          "category": "humanitarian crisis",
          "confidence": 0.19488604366779327,
          "weight": 0.0,
          "ai_model": "XLM-RoBERTa-Large-XNLI",
          "ai_confidence_score": "19.5%",
          "detected_lang": "local",
          "is_translated": false,
          "country": "Greece"
        },
        {
          "title": "Οι TikTokers της διπλανής πόρτας - O χορός των likes και των εκατοντάδων χιλιάδων ευρώ",
          "translated_title": null,
          "link": "https://www.protothema.gr/greece/article/1770548/oi-tiktokers-tis-diplanis-portas/?utm_source=rss",
          "date": "Sun, 08 Feb 2026 18:34:22 +0200",
          "category": "neutral news",
          "confidence": 0.19482214748859406,
          "weight": 0.0,
          "ai_model": "XLM-RoBERTa-Large-XNLI",
          "ai_confidence_score": "19.5%",
          "detected_lang": "local",
          "is_translated": false,
          "country": "Greece"
        },
        {
          "title": "Ο Παναθηναϊκός πέρασε άνετα από την Καρδίτσα επικρατώντας με 78-53",
          "translated_title": null,
          "link": "https://www.protothema.gr/sports/article/1770547/o-panathinaikos-perase-aneta-apo-tin-karditsa-epikratodas-me-78-53/?utm_source=rss",
          "date": "Sun, 08 Feb 2026 17:55:00 +0200",
          "category": "violent protest",
          "confidence": 0.3693055510520935,
          "weight": 0.0,
          "ai_model": "XLM-RoBERTa-Large-XNLI",
          "ai_confidence_score": "36.9%",
          "detected_lang": "local",
          "is_translated": false,
          "country": "Greece"
        },
        {
          "title": "Στίβος: Πανελλήνιο ρεκόρ στα 60μ εμπόδια από την Μπακογιάννη, βίντεο",
          "translated_title": null,
          "link": "https://www.protothema.gr/sports/article/1770545/stivos-panellinio-rekor-sta-60m-ebodia-apo-tin-bakogianni/?utm_source=rss",
          "date": "Sun, 08 Feb 2026 17:43:00 +0200",
          "category": "military conflict",
          "confidence": 0.35733747482299805,
          "weight": 0.0,
          "ai_model": "XLM-RoBERTa-Large-XNLI",
          "ai_confidence_score": "35.7%",
          "detected_lang": "local",
          "is_translated": false,
          "country": "Greece"
        },
        {
          "title": "Σαρωτική νίκη για την «εκλεκτή» του Τραμπ στην Ιαπωνία, εξασφαλίζει πάνω από τα δύο τρίτα των εδρών η Τακαΐτσι",
          "translated_title": null,
          "link": "https://www.protothema.gr/world/article/1770544/sarotiki-niki-gia-tin-takaitsi-stin-iaponia-exasfalizei-pano-apo-ta-duo-trita-ton-edron/?utm_source=rss",
          "date": "Sun, 08 Feb 2026 17:33:00 +0200",
          "category": "military conflict",
          "confidence": 0.19261500239372253,
          "weight": 0.0,
          "ai_model": "XLM-RoBERTa-Large-XNLI",
          "ai_confidence_score": "19.3%",
          "detected_lang": "local",
          "is_translated": false,
          "country": "Greece"
        },
        {
          "title": "Άρης - ΠΑΟΚ, Live το ντέρμπι της Θεσσαλονίκης: 0-0 (Α' ημίχρονο)",
          "translated_title": null,
          "link": "https://www.protothema.gr/sports/article/1770542/aris-paok-live-to-derbi-tis-thessalonikis/?utm_source=rss",
          "date": "Sun, 08 Feb 2026 19:12:41 +0200",
          "category": "military conflict",
          "confidence": 0.2247314453125,
          "weight": 0.0,
          "ai_model": "XLM-RoBERTa-Large-XNLI",
          "ai_confidence_score": "22.5%",
          "detected_lang": "local",
          "is_translated": false,
          "country": "Greece"
        },
        {
          "title": "Η Ιωάννα Τούνη αυτοτρολάρεται από τη Σαουδική Αραβία: Το παίζω high society ενώ κατάγομαι από το Πετρίτσι Σερρών",
          "translated_title": null,
          "link": "https://www.protothema.gr/life-style/article/1770541/i-ioanna-touni-autotrolaretai-apo-ti-saoudiki-aravia-to-paizo-high-society-eno-katagomai-apo-to-petritsi-serron/?utm_source=rss",
          "date": "Sun, 08 Feb 2026 17:27:17 +0200",
          "category": "neutral news",
          "confidence": 0.34287145733833313,
          "weight": 0.0,
          "ai_model": "XLM-RoBERTa-Large-XNLI",
          "ai_confidence_score": "34.3%",
          "detected_lang": "local",
          "is_translated": false,
          "country": "Greece"
        },
        {
          "title": "Η βαθμολογία μετά τη νίκη της ΑΕΚ στις Σέρρες",
          "translated_title": null,
          "link": "https://www.protothema.gr/sports/article/1770538/i-vathmologia-meta-ti-niki-tis-aek-stis-serres/?utm_source=rss",
          "date": "Sun, 08 Feb 2026 17:56:00 +0200",
          "category": "violent protest",
          "confidence": 0.3225856125354767,
          "weight": 0.0,
          "ai_model": "XLM-RoBERTa-Large-XNLI",
          "ai_confidence_score": "32.3%",
          "detected_lang": "local",
          "is_translated": false,
          "country": "Greece"
        },
        {
          "title": "Ζελένσκι: «Νόμιμος στόχος για τους βομβαρδισμούς της Ουκρανίας είναι ο ρωσικός ενεργειακός τομέας»",
          "translated_title": null,
          "link": "https://www.protothema.gr/world/article/1770536/zelenski-nomimos-stohos-gia-tous-vomvardismous-tis-oukranias-einai-o-rosikos-energeiakos-tomeas/?utm_source=rss",
          "date": "Sun, 08 Feb 2026 17:23:00 +0200",
          "category": "military conflict",
          "confidence": 0.3710954785346985,
          "weight": 0.0,
          "ai_model": "XLM-RoBERTa-Large-XNLI",
          "ai_confidence_score": "37.1%",
          "detected_lang": "local",
          "is_translated": false,
          "country": "Greece"
        }
      ]
    },
    "Iran": {
      "index": 4.33,
      "raw_score": 16.26,
      "events": [
        {
          "title": "Iran ready for nuclear-focused talks, rejects US military build-up",
          "translated_title": "Iran ready for nuclear-focused talks, rejects US military build-up",
          "link": "https://www.aljazeera.com/news/2026/2/8/iran-ready-for-nuclear-focused-talks-rejects-us-military-build-up?traffic_source=rss",
          "date": "Sun, 08 Feb 2026 16:03:39 +0000",
          "category": "military conflict",
          "confidence": 0.9611256718635559,
          "weight": 9.611256718635559,
          "ai_model": "XLM-RoBERTa-Large-XNLI",
          "ai_confidence_score": "96.1%",
          "detected_lang": "en",
          "is_translated": false,
          "country": "Iran"
        },
        {
          "title": "UK PM’s top aide quits over Mandelson’s links to Epstein",
          "translated_title": "UK PM’s top aide quits over Mandelson’s links to Epstein",
          "link": "https://www.aljazeera.com/news/2026/2/8/uk-pms-top-aide-quits-over-mandelsons-links-to-epstein?traffic_source=rss",
          "date": "Sun, 08 Feb 2026 17:11:13 +0000",
          "category": "political crisis",
          "confidence": 0.9296148419380188,
          "weight": 5.577689051628113,
          "ai_model": "XLM-RoBERTa-Large-XNLI",
          "ai_confidence_score": "93.0%",
          "detected_lang": "local",
          "is_translated": true,
          "country": "Iran",
          "translation_engine": "Google Neural MT"
        },
        {
          "title": "Somalia’s president on Israel, Somaliland and rising regional tension",
          "translated_title": "Somalia’s president on Israel, Somaliland and rising regional tension",
          "link": "https://www.aljazeera.com/video/talk-to-al-jazeera/2026/2/8/somalias-president-on-israel-somaliland-and-rising-regional-tension?traffic_source=rss",
          "date": "Sun, 08 Feb 2026 14:39:17 +0000",
          "category": "political crisis",
          "confidence": 0.7269511222839355,
          "weight": 4.361706733703613,
          "ai_model": "XLM-RoBERTa-Large-XNLI",
          "ai_confidence_score": "72.7%",
          "detected_lang": "local",
          "is_translated": true,
          "country": "Iran",
          "translation_engine": "Google Neural MT"
        },
        {
          "title": "Who is Leqaa Kordia, the Columbia protester still in ICE detention?",
          "translated_title": null,
          "link": "https://www.aljazeera.com/news/2026/2/8/who-is-leqaa-kordia-the-columbia-protester-still-in-ice-detention?traffic_source=rss",
          "date": "Sun, 08 Feb 2026 16:10:52 +0000",
          "category": "political crisis",
          "confidence": 0.20466995239257812,
          "weight": 0.0,
          "ai_model": "XLM-RoBERTa-Large-XNLI",
          "ai_confidence_score": "20.5%",
          "detected_lang": "en",
          "is_translated": false,
          "country": "Iran"
        },
        {
          "title": "Thai PM Anutin’s party takes early lead in general election race",
          "translated_title": null,
          "link": "https://www.aljazeera.com/news/2026/2/8/thai-pm-anutins-party-takes-early-lead-in-general-election-race?traffic_source=rss",
          "date": "Sun, 08 Feb 2026 16:10:00 +0000",
          "category": "neutral news",
          "confidence": 0.23395200073719025,
          "weight": 0.0,
          "ai_model": "XLM-RoBERTa-Large-XNLI",
          "ai_confidence_score": "23.4%",
          "detected_lang": "local",
          "is_translated": false,
          "country": "Iran"
        },
        {
          "title": "PM Sanae Takaichi’s party set for majority in Japan parliamentary elections",
          "translated_title": null,
          "link": "https://www.aljazeera.com/news/2026/2/8/pm-sanae-takaichis-party-set-for-majority-in-japan-parliamentary-elections?traffic_source=rss",
          "date": "Sun, 08 Feb 2026 15:10:36 +0000",
          "category": "political crisis",
          "confidence": 0.3127371668815613,
          "weight": 0.0,
          "ai_model": "XLM-RoBERTa-Large-XNLI",
          "ai_confidence_score": "31.3%",
          "detected_lang": "local",
          "is_translated": false,
          "country": "Iran"
        },
        {
          "title": "Trump hosts Honduras’s new president Asfura at Mar-a-Lago in US",
          "translated_title": null,
          "link": "https://www.aljazeera.com/news/2026/2/8/trump-hosts-hondurass-new-president-asfura-at-mar-a-lago-in-us?traffic_source=rss",
          "date": "Sun, 08 Feb 2026 14:48:24 +0000",
          "category": "neutral news",
          "confidence": 0.23945413529872894,
          "weight": 0.0,
          "ai_model": "XLM-RoBERTa-Large-XNLI",
          "ai_confidence_score": "23.9%",
          "detected_lang": "local",
          "is_translated": false,
          "country": "Iran"
        },
        {
          "title": "Understanding the value of gold: Prices, global reserves, and market trends",
          "translated_title": null,
          "link": "https://www.aljazeera.com/economy/2026/2/8/understanding-the-value-of-gold-prices-global-reserves-and-market-trends?traffic_source=rss",
          "date": "Sun, 08 Feb 2026 14:27:04 +0000",
          "category": "violent protest",
          "confidence": 0.3663429021835327,
          "weight": 0.0,
          "ai_model": "XLM-RoBERTa-Large-XNLI",
          "ai_confidence_score": "36.6%",
          "detected_lang": "en",
          "is_translated": false,
          "country": "Iran"
        },
        {
          "title": "England beat Nepal by four runs; avoid shock at T20 World Cup",
          "translated_title": null,
          "link": "https://www.aljazeera.com/sports/2026/2/8/england-beat-nepal-by-4-runs-avoid-shock-at-t20-world-cup?traffic_source=rss",
          "date": "Sun, 08 Feb 2026 13:58:27 +0000",
          "category": "neutral news",
          "confidence": 0.5702053904533386,
          "weight": 0.0,
          "ai_model": "XLM-RoBERTa-Large-XNLI",
          "ai_confidence_score": "57.0%",
          "detected_lang": "en",
          "is_translated": false,
          "country": "Iran"
        },
        {
          "title": "US federal agent breaks pet dog’s rib in Tennessee",
          "translated_title": null,
          "link": "https://www.aljazeera.com/video/newsfeed/2026/2/8/us-federal-agent-breaks-pet-dogs-rib-in-tennessee?traffic_source=rss",
          "date": "Sun, 08 Feb 2026 13:56:14 +0000",
          "category": "military conflict",
          "confidence": 0.27610230445861816,
          "weight": 0.0,
          "ai_model": "XLM-RoBERTa-Large-XNLI",
          "ai_confidence_score": "27.6%",
          "detected_lang": "local",
          "is_translated": false,
          "country": "Iran"
        },
        {
          "title": "Trump won’t apologise despite backlash over video depicting Obamas as apes",
          "translated_title": null,
          "link": "https://www.aljazeera.com/video/newsfeed/2026/2/8/trump-wont-apologise-despite-backlash-over-video-depicting-obamas-as-apes?traffic_source=rss",
          "date": "Sun, 08 Feb 2026 13:38:50 +0000",
          "category": "violent protest",
          "confidence": 0.323445588350296,
          "weight": 0.0,
          "ai_model": "XLM-RoBERTa-Large-XNLI",
          "ai_confidence_score": "32.3%",
          "detected_lang": "local",
          "is_translated": false,
          "country": "Iran"
        },
        {
          "title": "LIVE: Liverpool vs Manchester City – Premier League",
          "translated_title": null,
          "link": "https://www.aljazeera.com/sports/liveblog/2026/2/8/live-liverpool-vs-manchester-city-premier-league?traffic_source=rss",
          "date": "Sun, 08 Feb 2026 13:30:00 +0000",
          "category": "violent protest",
          "confidence": 0.2479282170534134,
          "weight": 0.0,
          "ai_model": "XLM-RoBERTa-Large-XNLI",
          "ai_confidence_score": "24.8%",
          "detected_lang": "local",
          "is_translated": false,
          "country": "Iran"
        },
        {
          "title": "India and Malaysia pledge to bolster trade, defence collaborations",
          "translated_title": null,
          "link": "https://www.aljazeera.com/news/2026/2/8/india-and-malaysia-pledge-to-bolster-trade-defence-collaborations?traffic_source=rss",
          "date": "Sun, 08 Feb 2026 12:55:52 +0000",
          "category": "peaceful diplomacy",
          "confidence": 0.317083477973938,
          "weight": 0.0,
          "ai_model": "XLM-RoBERTa-Large-XNLI",
          "ai_confidence_score": "31.7%",
          "detected_lang": "en",
          "is_translated": false,
          "country": "Iran"
        },
        {
          "title": "Iran FM says Tehran ready for deal with US with peaceful nuclear enrichment",
          "translated_title": null,
          "link": "https://www.aljazeera.com/video/newsfeed/2026/2/8/iran-fm-says-tehran-ready-for-deal-with-us-with-peaceful-nuclear-enrichment?traffic_source=rss",
          "date": "Sun, 08 Feb 2026 16:28:39 +0000",
          "category": "peaceful diplomacy",
          "confidence": 0.7797858119010925,
          "weight": -1.559571623802185,
          "ai_model": "XLM-RoBERTa-Large-XNLI",
          "ai_confidence_score": "78.0%",
          "detected_lang": "en",
          "is_translated": false,
          "country": "Iran"
        },
        {
          "title": "How reconstruction became Israel’s new weapon of ‘silent transfer’ in Gaza",
          "translated_title": null,
          "link": "https://www.aljazeera.com/features/2026/2/8/how-reconstruction-became-israels-new-weapon-of-silent-transfer-in-gaza?traffic_source=rss",
          "date": "Sun, 08 Feb 2026 14:23:51 +0000",
          "category": "peaceful diplomacy",
          "confidence": 0.864315927028656,
          "weight": -1.728631854057312,
          "ai_model": "XLM-RoBERTa-Large-XNLI",
          "ai_confidence_score": "86.4%",
          "detected_lang": "local",
          "is_translated": false,
          "country": "Iran"
        }
      ]
    },
    "Iraq": {
      "index": 4.79,
      "raw_score": 22.3,
      "events": [
        {
          "title": "Two Palestinians killed in Israeli attacks in the Gaza Strip",
          "translated_title": "Two Palestinians killed in Israeli attacks in the Gaza Strip",
          "link": "https://www.newarab.com/news/two-palestinians-killed-israeli-attacks-gaza-strip",
          "date": "Sun, 08 Feb 2026 15:11:28 +0000",
          "category": "military conflict",
          "confidence": 0.9512034058570862,
          "weight": 9.512034058570862,
          "ai_model": "XLM-RoBERTa-Large-XNLI",
          "ai_confidence_score": "95.1%",
          "detected_lang": "en",
          "is_translated": false,
          "country": "Iraq"
        },
        {
          "title": "Two Palestinians shot at Qalandiya amid Israeli settler attacks",
          "translated_title": "Two Palestinians shot at Qalandiya amid Israeli settler attacks",
          "link": "https://www.newarab.com/news/two-palestinians-shot-qalandiya-amid-israeli-settler-attacks",
          "date": "Sun, 08 Feb 2026 14:24:28 +0000",
          "category": "military conflict",
          "confidence": 0.8305724263191223,
          "weight": 8.305724263191223,
          "ai_model": "XLM-RoBERTa-Large-XNLI",
          "ai_confidence_score": "83.1%",
          "detected_lang": "en",
          "is_translated": false,
          "country": "Iraq"
        },
        {
          "title": "Iraq: Baghdad merchants protests new customs tariffs amid debt",
          "translated_title": null,
          "link": "https://www.newarab.com/news/iraq-baghdad-merchants-protests-new-customs-tariffs-amid-debt",
          "date": "Sun, 08 Feb 2026 16:13:03 +0000",
          "category": "economic crisis",
          "confidence": 0.6655163168907166,
          "weight": 2.662065267562866,
          "ai_model": "XLM-RoBERTa-Large-XNLI",
          "ai_confidence_score": "66.6%",
          "detected_lang": "en",
          "is_translated": false,
          "country": "Iraq"
        },
        {
          "title": "Over 154,000 evacuated in Morocco amid 'exceptional' floods",
          "translated_title": null,
          "link": "https://www.newarab.com/news/over-154000-evacuated-morocco-amid-exceptional-floods",
          "date": "Sun, 08 Feb 2026 17:28:51 +0000",
          "category": "humanitarian crisis",
          "confidence": 0.6072469353675842,
          "weight": 1.8217408061027527,
          "ai_model": "XLM-RoBERTa-Large-XNLI",
          "ai_confidence_score": "60.7%",
          "detected_lang": "en",
          "is_translated": false,
          "country": "Iraq"
        },
        {
          "title": "Iran sentences Narges Mohammadi to six years in prison: lawyer",
          "translated_title": null,
          "link": "https://www.newarab.com/news/iran-sentences-narges-mohammadi-six-years-prison-lawyer",
          "date": "Sun, 08 Feb 2026 17:35:54 +0000",
          "category": "neutral news",
          "confidence": 0.2944425940513611,
          "weight": 0.0,
          "ai_model": "XLM-RoBERTa-Large-XNLI",
          "ai_confidence_score": "29.4%",
          "detected_lang": "en",
          "is_translated": false,
          "country": "Iraq"
        },
        {
          "title": "Netanyahu 'to press Trump with demands on Iran talks'",
          "translated_title": null,
          "link": "https://www.newarab.com/news/netanyahu-press-trump-demands-iran-talks",
          "date": "Sun, 08 Feb 2026 17:09:34 +0000",
          "category": "political crisis",
          "confidence": 0.28884458541870117,
          "weight": 0.0,
          "ai_model": "XLM-RoBERTa-Large-XNLI",
          "ai_confidence_score": "28.9%",
          "detected_lang": "en",
          "is_translated": false,
          "country": "Iraq"
        },
        {
          "title": "Israeli bobsled team say flat 'burgled' during Olympics training",
          "translated_title": null,
          "link": "https://www.newarab.com/news/israeli-bobsled-team-say-flat-burgled-during-olympics-training",
          "date": "Sun, 08 Feb 2026 17:06:34 +0000",
          "category": "violent protest",
          "confidence": 0.9059117436408997,
          "weight": 0.0,
          "ai_model": "XLM-RoBERTa-Large-XNLI",
          "ai_confidence_score": "90.6%",
          "detected_lang": "en",
          "is_translated": false,
          "country": "Iraq"
        },
        {
          "title": "Greece to detain Moroccan over fatal migrant boat collision",
          "translated_title": null,
          "link": "https://www.newarab.com/news/greece-detain-moroccan-over-fatal-migrant-boat-collision",
          "date": "Sun, 08 Feb 2026 15:14:05 +0000",
          "category": "military conflict",
          "confidence": 0.44848161935806274,
          "weight": 0.0,
          "ai_model": "XLM-RoBERTa-Large-XNLI",
          "ai_confidence_score": "44.8%",
          "detected_lang": "en",
          "is_translated": false,
          "country": "Iraq"
        },
        {
          "title": "‘From the river to the sea’ faces ban in Australia's Queensland",
          "translated_title": null,
          "link": "https://www.newarab.com/news/river-sea-faces-ban-australias-queensland",
          "date": "Sun, 08 Feb 2026 14:48:41 +0000",
          "category": "neutral news",
          "confidence": 0.26155877113342285,
          "weight": 0.0,
          "ai_model": "XLM-RoBERTa-Large-XNLI",
          "ai_confidence_score": "26.2%",
          "detected_lang": "local",
          "is_translated": false,
          "country": "Iraq"
        },
        {
          "title": "UK foreign office to review pay-off to Epstein-linked Mandelson",
          "translated_title": null,
          "link": "https://www.newarab.com/news/uk-foreign-office-review-pay-epstein-linked-mandelson",
          "date": "Sun, 08 Feb 2026 14:42:43 +0000",
          "category": "military conflict",
          "confidence": 0.24579429626464844,
          "weight": 0.0,
          "ai_model": "XLM-RoBERTa-Large-XNLI",
          "ai_confidence_score": "24.6%",
          "detected_lang": "en",
          "is_translated": false,
          "country": "Iraq"
        },
        {
          "title": "Ethiopia demands Eritrea to withdraw troops from its territory",
          "translated_title": null,
          "link": "https://www.newarab.com/news/ethiopia-demands-eritrea-withdraw-troops-its-territory",
          "date": "Sun, 08 Feb 2026 14:02:39 +0000",
          "category": "peaceful diplomacy",
          "confidence": 0.18984587490558624,
          "weight": 0.0,
          "ai_model": "XLM-RoBERTa-Large-XNLI",
          "ai_confidence_score": "19.0%",
          "detected_lang": "en",
          "is_translated": false,
          "country": "Iraq"
        },
        {
          "title": "Girls as young as four subjected to FGM in Iraqi Kurdistan",
          "translated_title": null,
          "link": "https://www.newarab.com/news/girls-young-four-subjected-fgm-iraqi-kurdistan",
          "date": "Sun, 08 Feb 2026 13:55:19 +0000",
          "category": "military conflict",
          "confidence": 0.3703116774559021,
          "weight": 0.0,
          "ai_model": "XLM-RoBERTa-Large-XNLI",
          "ai_confidence_score": "37.0%",
          "detected_lang": "en",
          "is_translated": false,
          "country": "Iraq"
        },
        {
          "title": "Ukraine urges more peace talks, says only Trump can broker deal",
          "translated_title": null,
          "link": "https://www.newarab.com/news/ukraine-urges-more-peace-talks-says-only-trump-can-broker-deal",
          "date": "Sun, 08 Feb 2026 13:02:48 +0000",
          "category": "political crisis",
          "confidence": 0.4014851152896881,
          "weight": 0.0,
          "ai_model": "XLM-RoBERTa-Large-XNLI",
          "ai_confidence_score": "40.1%",
          "detected_lang": "en",
          "is_translated": false,
          "country": "Iraq"
        },
        {
          "title": "Ex-French minister quits Arab World Institute over Epstein links",
          "translated_title": null,
          "link": "https://www.newarab.com/news/ex-french-minister-quits-arab-world-institute-over-epstein-links",
          "date": "Sun, 08 Feb 2026 12:34:53 +0000",
          "category": "political crisis",
          "confidence": 0.19849562644958496,
          "weight": 0.0,
          "ai_model": "XLM-RoBERTa-Large-XNLI",
          "ai_confidence_score": "19.8%",
          "detected_lang": "en",
          "is_translated": false,
          "country": "Iraq"
        },
        {
          "title": "Two killed, others missing as flash floods hit northwest Syria",
          "translated_title": null,
          "link": "https://www.newarab.com/news/two-killed-others-missing-flash-floods-hit-northwest-syria",
          "date": "Sun, 08 Feb 2026 11:38:47 +0000",
          "category": "humanitarian crisis",
          "confidence": 0.3133925199508667,
          "weight": 0.0,
          "ai_model": "XLM-RoBERTa-Large-XNLI",
          "ai_confidence_score": "31.3%",
          "detected_lang": "en",
          "is_translated": false,
          "country": "Iraq"
        }
      ]
    },
    "Syria": {
      "index": 4.88,
      "raw_score": 23.71,
      "events": [
        {
          "title": "US transfers ISIL detainees to Iraq as northeast Syria base draws down - Al Jazeera",
          "translated_title": "US transfers ISIL detainees to Iraq as northeast Syria base draws down - Al Jazeera",
          "link": "https://news.google.com/rss/articles/CBMirwFBVV95cUxPTXZ2UEVYLXdIeFpVRmwtZ1pXQUE0NGRhVmxmLUd4bXpqcWJUS3QtX0tiRWlHa2ptSzdmLVE4Tnc5MkpRU05XM1dnam1oR2xUenB0NGpDbFBpXzhVQURJckh5YlR6UWtfdWZsLWozNHFSOXpqT2xsSGJ5UXh2Y1ZGcmxqeVNLcUdxcEJqOXI3RlAyWFZKTHRUZVp2NlFlOE9vX0JTaUM1UXlSaE1kZ0lz0gG0AUFVX3lxTE9WTm5FbDRtRVhJQWNoaTFvZVhjTzhWOWxRMnhxR3QtN1JsT283NDFtUkV6YXlHbWg3Qkh2N2s5ZEVlNEdGVG1rd2ZQaUVMd1dJbWlVS1I4MER6Q3ViUkdsdXZRWGtESWtHMnNaeFNZdUVrRF9SbThvS3pFaDh0d3ozRTBVbm5sZWgweFk3cUNfTFVXZUJGVlU3TTlZbHp6aEFyT19tcFprUDhVR3czNVF4YzhVag?oc=5",
          "date": "Sat, 07 Feb 2026 16:53:43 GMT",
          "category": "military conflict",
          "confidence": 0.7809527516365051,
          "weight": 7.809527516365051,
          "ai_model": "XLM-RoBERTa-Large-XNLI",
          "ai_confidence_score": "78.1%",
          "detected_lang": "en",
          "is_translated": false,
          "country": "Syria"
        },
        {
          "title": "Kurds in northeastern Syria fear end of autonomy - DW.com",
          "translated_title": "Kurds in northeastern Syria fear end of autonomy - DW.com",
          "link": "https://news.google.com/rss/articles/CBMijgFBVV95cUxNdnRDUFNhSGthd0laV2lTMVc4QWFjeWVrUE1TNWxVckRVdVVKSHRFQkNILUVESjNOcWs5TFVLc0hqckxObGw3MGV2ZlJQLTlWc2dsMTVlR19sRUQwWU9ySlQ2LXcwNU9wTEVzcVBfQktuRWdoMjAtbmNFYl9kbWRtNkFfSG5KTS0yLWJKUHhn?oc=5",
          "date": "Sat, 07 Feb 2026 01:18:45 GMT",
          "category": "political crisis",
          "confidence": 0.824661910533905,
          "weight": 4.94797146320343,
          "ai_model": "XLM-RoBERTa-Large-XNLI",
          "ai_confidence_score": "82.5%",
          "detected_lang": "en",
          "is_translated": false,
          "country": "Syria"
        },
        {
          "title": "Inside the demise of Syria’s Kurdish autonomy - The Jerusalem Post",
          "translated_title": "Inside the demise of Syria’s Kurdish autonomy - The Jerusalem Post",
          "link": "https://news.google.com/rss/articles/CBMiXEFVX3lxTFB1TktJUm1QemVPUTZXX1pYWTNsWXFBUUstTldPTE5ZeUNHRHZ5RFVqdDJKOGFSVjNXZ3FCWm0wVWJLZENqREVyNlJtYXMxTkdMRERiVl9UR09CZVBs?oc=5",
          "date": "Sat, 07 Feb 2026 08:11:06 GMT",
          "category": "political crisis",
          "confidence": 0.8238089680671692,
          "weight": 4.942853808403015,
          "ai_model": "XLM-RoBERTa-Large-XNLI",
          "ai_confidence_score": "82.4%",
          "detected_lang": "local",
          "is_translated": true,
          "country": "Syria",
          "translation_engine": "Google Neural MT"
        },
        {
          "title": "New doubts cast on Syrian Kurdish woman's braid removal incident - The New Arab",
          "translated_title": "New doubts cast on Syrian Kurdish woman's braid removal incident - The New Arab",
          "link": "https://news.google.com/rss/articles/CBMikwFBVV95cUxOb29HSmh4blpLNmkzcTB3ak5XX2djZmJjMW83emNENm8tR0hFbmhrNE9Fa2M5Skh1OURlcjVHNVp3U3M5UmFmWFBFVkFlRlcyMzZNZmtMZFlJVW41RGhCeVFOeE9KTm9yRFZ2U011X2doYWpBX1BZUmpVUU9SR2NQRk1WeTRCWUFzUjhEbFFWTkdRUWvSAZgBQVVfeXFMUG80MWRHeVp5WmFtOWNMS2lTS1hvZzd3RHRnUkJRdzFGSEdfd1dCajZpY2dFVElvdDVQNEhadWR5Y3ZGZ1FrZHlBT2R0WDJmRV9acWwxX19qNGtqV0c5OVdzZVJ0TDZrRG1aVnYtd2dib09ZYkI3X0FJR2NKem84U1VHaTBPVi10bVZyLWozcFh3MkJZOUZvcTE?oc=5",
          "date": "Sat, 07 Feb 2026 13:29:53 GMT",
          "category": "political crisis",
          "confidence": 0.5174497961997986,
          "weight": 3.1046987771987915,
          "ai_model": "XLM-RoBERTa-Large-XNLI",
          "ai_confidence_score": "51.7%",
          "detected_lang": "en",
          "is_translated": false,
          "country": "Syria"
        },
        {
          "title": "Saudi deepens ties with Syria's new leaders through major investment package - Reuters",
          "translated_title": null,
          "link": "https://news.google.com/rss/articles/CBMipwFBVV95cUxOdU9keE44Nk5SS1B1alo2b1NyQTlWQk9Mc0pnM29TODNZTFFXSnZQYUtvVGZ5VHYtQXQtb1VqdmRXdnhhNGZyTFdySzd6VndSc2JORVdPWEp2S0RJcnpNTWFkMExqcmpnU1JJR3NBZVJ6V1BDYjZmeFRtTFNMWmUwcVh6NWJSZXpEYU9XSFFEY1NwVEJrTGhraEo0UmtwZlpFdDFEMTNxbw?oc=5",
          "date": "Sat, 07 Feb 2026 14:17:51 GMT",
          "category": "political crisis",
          "confidence": 0.4849865436553955,
          "weight": 2.909919261932373,
          "ai_model": "XLM-RoBERTa-Large-XNLI",
          "ai_confidence_score": "48.5%",
          "detected_lang": "en",
          "is_translated": false,
          "country": "Syria"
        },
        {
          "title": "The hard but right road in Syria - The Hill",
          "translated_title": null,
          "link": "https://news.google.com/rss/articles/CBMiiAFBVV95cUxPWXN4c3p6V3N6N0RJRi1tRGhVUWdzZ2NQWTYta0x6QjNrRnlTRXFwaDljN0dkWUVQcENLLWZvZGlIN3BPZ0RJZnYtX2dEWFZ0ckt3UGF2ekNYTFB6NEhGZFg4ZTBnR3pONVREOFAxazB3Y3QwYUY0OXlsT0pJbm5kNjlwNEhiSVpo0gGOAUFVX3lxTFBXa0gtRjNSZTdrMk1PNUk2Q2xBczNkdC1qbkF0UFIxaDJRSTU2UGU0SXM5Z25Ua282ZXRDenExTDF4OEcwNkJqNVdSNVNlNGs0X1NGRlFDVEpmUlVyUUpKaEpXSldKUm5NalJpZGh6R1prOWxnbjA1QmxYc3lNeE5rR3BKTHkwWGRrQjFFclE?oc=5",
          "date": "Fri, 06 Feb 2026 19:00:00 GMT",
          "category": "neutral news",
          "confidence": 0.49664318561553955,
          "weight": 0.0,
          "ai_model": "XLM-RoBERTa-Large-XNLI",
          "ai_confidence_score": "49.7%",
          "detected_lang": "en",
          "is_translated": false,
          "country": "Syria"
        },
        {
          "title": "Syria and Saudi Arabia sign multibillion-dollar investment deals to boost economy - AP News",
          "translated_title": null,
          "link": "https://news.google.com/rss/articles/CBMirgFBVV95cUxNRmowYjRqUFJUR1hOek1VWnRsTEVJZnVzbV81WHJxRTBxczBVY1pKYTlISUFBR1F2emlNLWY5bHJSMzEyNTduUF9MN01MZnFLTWtVM2RFcURmVTFUVUE5eTJLUXMyR2pIVW9yYnRsTTYySkNrQzhleEZoTWsxci0tZTR1MTBPYVpOSmw3OHdrOTRPNGQ0R0VHSEtVbVFqc3phd3p2TWNydmdLc0dvV3c?oc=5",
          "date": "Sat, 07 Feb 2026 16:26:00 GMT",
          "category": "violent protest",
          "confidence": 0.3675185739994049,
          "weight": 0.0,
          "ai_model": "XLM-RoBERTa-Large-XNLI",
          "ai_confidence_score": "36.8%",
          "detected_lang": "en",
          "is_translated": false,
          "country": "Syria"
        },
        {
          "title": "Saudis Announce New Investments in Syria, a Sign of Deepening Ties - The New York Times",
          "translated_title": null,
          "link": "https://news.google.com/rss/articles/CBMinAFBVV95cUxOeTVTWWJGaDBuWWFEeHViRDAwTGw1Z0FTendkMmRwUVhJWWZPQWhyeEZCTlNicFc1cmpLU204VXV3cUllaFRvVEVib2F3UmQ0MTE1czUtN2FRZ2lOVE83el9kMzgwU0xFdzlKOXpqQTF6Snc5dUtrWW1ONFJpWS1RbXRta3lwUFBIZUVhSXpFYno2MFJaSmc5UEkxc1c?oc=5",
          "date": "Sat, 07 Feb 2026 15:58:56 GMT",
          "category": "peaceful diplomacy",
          "confidence": 0.23981566727161407,
          "weight": 0.0,
          "ai_model": "XLM-RoBERTa-Large-XNLI",
          "ai_confidence_score": "24.0%",
          "detected_lang": "en",
          "is_translated": false,
          "country": "Syria"
        },
        {
          "title": "Saudi Arabia, Syria sign $5.3 billion in agreements across key sectors - Anadolu Ajansı",
          "translated_title": null,
          "link": "https://news.google.com/rss/articles/CBMisgFBVV95cUxPZHNlNEpJMWhrTGVySWJQYU0wWC1waVlHLTdQc3N6THZKRWMxR2NpMGNJRzFWbllIYW0yVGc0b2RXUjVtSEFpdEdIQUp6VEYzV3NrQ1lsSTYxdGhwTUMxQUhyaEhpNXNJODVlejBfQnNydjVHS3VTV193Nkw4bWF1cS15N1ozTHpwMV9Ma0k0YnA1N0E0dUI3S1lMVmwyeFd6MWpNVXlyemVzOGJHd3BYSHBB?oc=5",
          "date": "Sat, 07 Feb 2026 21:00:00 GMT",
          "category": "violent protest",
          "confidence": 0.26121413707733154,
          "weight": 0.0,
          "ai_model": "XLM-RoBERTa-Large-XNLI",
          "ai_confidence_score": "26.1%",
          "detected_lang": "local",
          "is_translated": false,
          "country": "Syria"
        },
        {
          "title": "Saudi Arabia to invest billions of dollars in Syria, including joint airline and telecom project - France 24",
          "translated_title": null,
          "link": "https://news.google.com/rss/articles/CBMiywFBVV95cUxOM09ZWHBWdXFJN183dUF5YW1lQmt3Z1VMNmg1T1J1VWs4UG5qdi1OVnRob2ZITHV2UjY2OGhGSXAyNVNON2FvTzdTWEs3bWxnelJJUE92cGVmSHF1ODhES1VncVFuTEdBcHlfbzRFTXpubWhNLXR2VU15azNaU196Ml9CRWxyS1hwajhOSHpYQzhiLXJqLWlVRXhKU1pQZ0Y4NWF3MEJ1ZGZqNEQzdHRyME96aEFKMnlrWmJWZUxIc0ptMGpsSS03S2lIQQ?oc=5",
          "date": "Sat, 07 Feb 2026 16:14:10 GMT",
          "category": "military conflict",
          "confidence": 0.16475160419940948,
          "weight": 0.0,
          "ai_model": "XLM-RoBERTa-Large-XNLI",
          "ai_confidence_score": "16.5%",
          "detected_lang": "en",
          "is_translated": false,
          "country": "Syria"
        },
        {
          "title": "Over 2,200 ISIS detainees transferred to Iraq from Syria: Iraqi official - The Times of Israel",
          "translated_title": null,
          "link": "https://news.google.com/rss/articles/CBMitwFBVV95cUxORTNHbEk5MmxsQ0dxMGV1MWRoMkcydW45cjV0YXJuOTdmQkNzaEcxcmJ0cUw5OXhiZ096dFg3bFdsVWZFTERjNk8wcXFDZ2lvakszWHV6Nkp4SE9mMEZ4Tkc4S2ZTNEZZWVZMNzJPaGVQUkdfSDdSblcxWGxoNW5mWXEyUG4zY0NqRzhJZmxWbUVyeXVna3FSaVBJUjh0bF9iRV9yU0czVEtWMW13WURvOUZueVBHTzA?oc=5",
          "date": "Sat, 07 Feb 2026 16:09:00 GMT",
          "category": "terrorist act",
          "confidence": 0.3098567724227905,
          "weight": 0.0,
          "ai_model": "XLM-RoBERTa-Large-XNLI",
          "ai_confidence_score": "31.0%",
          "detected_lang": "en",
          "is_translated": false,
          "country": "Syria"
        },
        {
          "title": "$1 billion for Syria’s Internet? Saudi Arabia’s historic telecom deal SilkLink, new joint airline push ex - Times of India",
          "translated_title": null,
          "link": "https://news.google.com/rss/articles/CBMilgJBVV95cUxPbERKb25fQWJ1ZkNGcloyb1M5RDFESGw1U2tyaWVxQldNeHh3RWxjWkpjRWxCTGNwS1NRbENtUDVzdERFR3lHYWg5eTFKcXQwZDZVdlFfNllTbUtjamNaUVZUOFg1OXpDWlFjaHhFMk9nSlg4SUxibXlYcVh0VDdFM0dqb3pkU1lGMXhYMVJNQ2ZuSUhObHA0dGsyaFVUaGJwY2V4X0RzT1RXcUZCTURZTkNYb21HNnFGMU1xc1lUYl94X0hHN2NhYmtLWHBsOVpoTkEtVjJuV1EtaEtMWEdtSnBJaDE4TVZ3NWNDdmxWR21vcVh0VWlOaUE2MjljdXQxczZQRHJIQlg4VFFLVFc3U3Nqbnkyd9IBmwJBVV95cUxNaE5NNnJSSTJHWVpfdTNqb1U3UXhVOWR3MHJzMUhZUUtkYmhDMjd0aEl4WHllb3pHREJqN1E3SHlHVjBmREh3Q3kxOUdlZzZ0SFlHaEwtNHZEZTU3eWRQWjVaZ1hGMzZCazZpSXRUbUhZUmRTWGlqZmhVX0xZVS14TW5nOERPc254bTdiQ0ltRjhkanVBVzhHU3pvZmpNeXF3RWZheFd2U2FOVmRKUXBlSWV6dmJCcFE3WHV6aHI0VVltQmxwWTNqbXRWOHdCS3dzOFRNNGhQZGxqeFppRExvUkNQdFJiX1pja0YxYWE4aVVVajlQZUx2TTN4RGhacVo1ajVXTVRxelE2ZFRMbEVoaUNrbzNCVVFzdFFz?oc=5",
          "date": "Sun, 08 Feb 2026 12:01:00 GMT",
          "category": "military conflict",
          "confidence": 0.20607921481132507,
          "weight": 0.0,
          "ai_model": "XLM-RoBERTa-Large-XNLI",
          "ai_confidence_score": "20.6%",
          "detected_lang": "local",
          "is_translated": false,
          "country": "Syria"
        },
        {
          "title": "Saudi Firms Agree to Rebuild Syrian Aviation and Mobile Networks - Bloomberg.com",
          "translated_title": null,
          "link": "https://news.google.com/rss/articles/CBMitgFBVV95cUxOdUMzRWRjdVl2MEhEdG5NLTR1U3A1WHotbFN3OUxmbE1CRE55c2dhUmVnN1FGUDkxT0dTcDR1RDU2RE5MVHJGbGE1NzhDb21wcmxvOXd2MkJzeUlHYms0cG9NWlpreldDWnEyX2lJbHNBdWpqcnRTcFFGaDZudks0Wmdhc2c3cU85a1ktcjlhdHkyQ0RwMmJLTHh1VldwdjBBbGktUUNPaS1CYXBrS0xXQ290akMtdw?oc=5",
          "date": "Sun, 08 Feb 2026 10:54:52 GMT",
          "category": "violent protest",
          "confidence": 0.28998056054115295,
          "weight": 0.0,
          "ai_model": "XLM-RoBERTa-Large-XNLI",
          "ai_confidence_score": "29.0%",
          "detected_lang": "en",
          "is_translated": false,
          "country": "Syria"
        },
        {
          "title": "Syria’s fragile unity faces new test in Sweida’s Druze heartland - thenationalnews.com",
          "translated_title": null,
          "link": "https://news.google.com/rss/articles/CBMiugFBVV95cUxPQjBMWXdYeDB2SjRGR0xYdXhjQm9iMEVIQzAtOVRQbDdjSHZrVFcxU0pRekd5dlM5b1dmZjVMWmtsQTlfQ0JRMjlKTjBTSTliN1poeDlyd2ZoYzZMYVNNQnAxUjY2RjJ6RmtySFRlQm9Qb25lMjJNOGg3cjUxbDNES29pNEkzMzJONUNlbFhhR3ZBY081TW8wLUxaeHBHWlVMTU9SZm4zR2VZVGtrV1lWdXlwMTd6WVhRalE?oc=5",
          "date": "Sat, 07 Feb 2026 12:30:46 GMT",
          "category": "peaceful diplomacy",
          "confidence": 0.22619333863258362,
          "weight": 0.0,
          "ai_model": "XLM-RoBERTa-Large-XNLI",
          "ai_confidence_score": "22.6%",
          "detected_lang": "local",
          "is_translated": false,
          "country": "Syria"
        },
        {
          "title": "Could Syria and Lebanon Join the Abraham Accords? - The National Interest",
          "translated_title": null,
          "link": "https://news.google.com/rss/articles/CBMiogFBVV95cUxOMnFNZ1BwejlEYWFuekJROUtRcU1rZ0dnNTNEZ2FiN2VkTmZCQU1OWHZfcUItcGJ5OGEyZHN6eGdTR0x5Yng0dTV5YTRLOHpkLWpWM2x3NVpqQ05nUFRFWUFaLUhEUS1nWEJ0b1VQSmFnVzFZV1M2STJLNEp2MkZQVldmcDBlTFpwc1h0YmliT3Y2WmdHNXRPTl9oblIteGN2NXc?oc=5",
          "date": "Sun, 08 Feb 2026 15:06:16 GMT",
          "category": "violent protest",
          "confidence": 0.19032014906406403,
          "weight": 0.0,
          "ai_model": "XLM-RoBERTa-Large-XNLI",
          "ai_confidence_score": "19.0%",
          "detected_lang": "en",
          "is_translated": false,
          "country": "Syria"
        }
      ]
    },
    "Bulgaria": {
      "index": 1.0,
      "raw_score": 0.0,
      "events": [
        {
          "title": "Bulgaria v Belgium: Gille and Vliegen clinch winning point - daviscup.com",
          "translated_title": null,
          "link": "https://news.google.com/rss/articles/CBMilAFBVV95cUxPUzEzSlNZcHNWTEdZNl9JRnptVERTODBvUUtVSF9GRG54aUZKajVmM0dlZ01ET1ZVN1N0V0tVdldfdFlGR2E2VGF6MUFuNzh3S1d6TnN6b2JYTG85X3huYl9aTzFZanY4dHhHZ0lJOC1kZVdkNUtTdkQ0YmZyY3dybldsNWJadUZxQzdLRkJwbDItQ1My?oc=5",
          "date": "Sun, 08 Feb 2026 13:59:25 GMT",
          "category": "violent protest",
          "confidence": 0.2854759097099304,
          "weight": 0.0,
          "ai_model": "XLM-RoBERTa-Large-XNLI",
          "ai_confidence_score": "28.5%",
          "detected_lang": "en",
          "is_translated": false,
          "country": "Bulgaria"
        },
        {
          "title": "Eurostat: 86.1% of Bulgarians own their own home - The Sofia Globe",
          "translated_title": null,
          "link": "https://news.google.com/rss/articles/CBMiiAFBVV95cUxPNXRpVlV0UUVKbFladGFyaThQMlFqdUluVFZnUGJ4akhhN2tyZFJleXh4YTdxMzNPZU5XWnotX25scXZiX1dEX2RRLXJPMEt4VzJLd0VmbWNYTFRBUk9KNFVrUUZlZkZGYm1OcTI2dFRfckpNT2dQdk00SFRycWh4THF0NjE5bmN1?oc=5",
          "date": "Sun, 08 Feb 2026 10:48:36 GMT",
          "category": "terrorist act",
          "confidence": 0.227690190076828,
          "weight": 0.0,
          "ai_model": "XLM-RoBERTa-Large-XNLI",
          "ai_confidence_score": "22.8%",
          "detected_lang": "en",
          "is_translated": false,
          "country": "Bulgaria"
        },
        {
          "title": "Tervel Zamfirov Wins Historic Medal for Bulgaria at the Winter Olympics - Novinite.com",
          "translated_title": null,
          "link": "https://news.google.com/rss/articles/CBMisgFBVV95cUxOaHhSWEF4aU0tQVUtS0RMSjY5emgyMkxRTzdELU55bW5MWFlJd0VxS3piUmp0TDlDTE1VSnYxRVpwUGZFeHVpY0tNRGw0eGpwQ2V5VmpjbGZCeFF2bF9QRjBabVlKUkRVNWFDTXdZR0RTT0dBSmFpR1BWU0o2LVhZTGk2WWg0TW1salM2ODZlRV9hS0gzU1E3Z3U0LXhwUkZBTjQ3aEVLSXpQZGlpamRNT3BB?oc=5",
          "date": "Sun, 08 Feb 2026 14:08:38 GMT",
          "category": "violent protest",
          "confidence": 0.3672083020210266,
          "weight": 0.0,
          "ai_model": "XLM-RoBERTa-Large-XNLI",
          "ai_confidence_score": "36.7%",
          "detected_lang": "en",
          "is_translated": false,
          "country": "Bulgaria"
        },
        {
          "title": "Rain and Falling Temperatures Expected Across Bulgaria on Monday - Novinite.com",
          "translated_title": null,
          "link": "https://news.google.com/rss/articles/CBMiqAFBVV95cUxOMlB2UFlQSWlyNFd0ZkN4TXNDaTZCTTFwT0toTUt2T2Y0aGY4MDdhSnBnRUxMTHhjTExZYTQ4NGQ5SVJjOEt0VXRfa0NZTndZclFKN0czLVItZkMycDlQVDdGQTQ4OGRzRWVlYzVmVDJYQXB0YnFmNHlCblhzMTU1ZmRuckZUclYtd0ZjVEVtSGFiNHNRdmlLV3huREJjZFpvQ1EySm9EQjU?oc=5",
          "date": "Sun, 08 Feb 2026 16:18:57 GMT",
          "category": "violent protest",
          "confidence": 0.2561858594417572,
          "weight": 0.0,
          "ai_model": "XLM-RoBERTa-Large-XNLI",
          "ai_confidence_score": "25.6%",
          "detected_lang": "en",
          "is_translated": false,
          "country": "Bulgaria"
        },
        {
          "title": "Bulgaria: New Socialist Party Leader Vows Unity and Action, Saying Victory Belongs to All - Novinite.com",
          "translated_title": null,
          "link": "https://news.google.com/rss/articles/CBMizwFBVV95cUxPeEY0LVUzdFdGZXlHZUczSXJoQkptaDBLeDFKbmV6dzE0aWo0YlZHZWhkV0U5aWdfREMyY2Q2VVBGbE1HbmdVOG44cEZHdHdYMk1qVUVzalFWVDF5SFpQUnNLS0t4Y2lqUFY0Q3FvQ0hhVDI5TldrOG93aEF6bzBJbzNtRzFyX1k3MGhqT2RCS3FxdGVyVHdqTk94ZTJYOExCVDVtdWJTSXg3SHRJckxTeGVaU1BIV3ZqbE9RaXBQWDhmaml3ekRnaVZQV0IxR0E?oc=5",
          "date": "Sun, 08 Feb 2026 10:10:34 GMT",
          "category": "neutral news",
          "confidence": 0.26267683506011963,
          "weight": 0.0,
          "ai_model": "XLM-RoBERTa-Large-XNLI",
          "ai_confidence_score": "26.3%",
          "detected_lang": "en",
          "is_translated": false,
          "country": "Bulgaria"
        },
        {
          "title": "Bulgaria's Petrohan Case: The Missing Ivaylo Kalushev and Two Others Found Dead in Forest Near Vratsa (DEVELOPING) - Novinite.com",
          "translated_title": null,
          "link": "https://news.google.com/rss/articles/CBMi9gFBVV95cUxONkFiNHFLaTViazdqNDhqbVpwNDYwREFTRU01ekNwb2FGR0I2cXR1Y3ZHaEdxNWlSa0hKNWpNWHZTZ08zalBpWkpZa1Y3UjVqN3AwbU93OGp3MzJvYjJGaDJlYUk4YzNkWlpMd0tZT1l2ZExFMEl0c2FQcXI4SUdxbWNoUkczb2s3UlZZRm52WUZWby1PQm5kcVduUWpabjdJbHh0ejVmTWpnQmNOZlBOSUxSY2lMUElGWEY1d09RWVFsY0xaZ2hxLVEyZzJRZ1B0OVI3eHlIcDJXWkRNSmZFc19LYnN1VWFwaUp3ZmNIbmEyMXI5Q0E?oc=5",
          "date": "Sun, 08 Feb 2026 14:09:39 GMT",
          "category": "humanitarian crisis",
          "confidence": 0.39862537384033203,
          "weight": 0.0,
          "ai_model": "XLM-RoBERTa-Large-XNLI",
          "ai_confidence_score": "39.9%",
          "detected_lang": "en",
          "is_translated": false,
          "country": "Bulgaria"
        },
        {
          "title": "Bulgaria Marches in Four Cities as Winter Olympics Open in Milano-Cortina - Novinite.com",
          "translated_title": null,
          "link": "https://news.google.com/rss/articles/CBMitAFBVV95cUxNYjNZWkduVnIweGVxeUJ5MkFYOHZVbXlrWGRqUks3NEk2ZEpYX3dTSlJjczROaTJrcG04OVd4RlJiSW45aHI2OERCMThwTWx3aW1lamswNkFNb2FrbklPY2dTSTNsMV9sdlZCTnl3NTZ4aU96UERKdXQyUTJXbHJqYjFKWEVVeklQM2hBb2pYTHZZajhJaUx3MDc4d2RObnM2dFREQzR5WjJiS1FWdXg5M0dlNGQ?oc=5",
          "date": "Fri, 06 Feb 2026 21:02:34 GMT",
          "category": "peaceful diplomacy",
          "confidence": 0.20340096950531006,
          "weight": 0.0,
          "ai_model": "XLM-RoBERTa-Large-XNLI",
          "ai_confidence_score": "20.3%",
          "detected_lang": "en",
          "is_translated": false,
          "country": "Bulgaria"
        },
        {
          "title": "Antarctica: Icons donated by Ecumenical Patriarch and Patriarch of Bulgaria installed at Bulgaria’s new research base - Orthodox Times",
          "translated_title": null,
          "link": "https://news.google.com/rss/articles/CBMi2gFBVV95cUxQRW5fSFZXM2dybUFLaFEzV0VWQzg5bk1sRnFhUVNzX0k4MlVpWEZxX1VYNUp0NkpLQU5OSTNBUWJOSmV3OGswOG4teU5rNnFnZ0tSUTF6SGQtcHFUeDZNaGJtU1hDclZJTlFGNlVSRTVXZm9XbnlCdHktUXZwSUNIbmRzSnJRck4wdzItUXJOQ1hsc29uSmFkRWJ5YWl6TGlPb3F5T01pbnVfYVRJZWQzeEl5a1VKU3NyRmZwN1VmUllrOFZQQkIxenFoT0ZLVHZ1VUJtMGd1d1dLUQ?oc=5",
          "date": "Sun, 08 Feb 2026 14:48:17 GMT",
          "category": "military conflict",
          "confidence": 0.22376124560832977,
          "weight": 0.0,
          "ai_model": "XLM-RoBERTa-Large-XNLI",
          "ai_confidence_score": "22.4%",
          "detected_lang": "local",
          "is_translated": false,
          "country": "Bulgaria"
        },
        {
          "title": "Peking Opera's New Year gala enchants Bulgaria, forging cultural bonds - People's Daily",
          "translated_title": null,
          "link": "https://news.google.com/rss/articles/CBMiY0FVX3lxTFBZSGdpWnJyV2ZaTXlWekczOE50eDl0YjlkcDZvX0tGbDRJN3FLWlEyME96d1VUVnh5OTJhdnp5YlczMWw5bXJNUWUwaGZlUllLdWNFN2poTjVoeEc3eXE3QjI3TQ?oc=5",
          "date": "Sat, 07 Feb 2026 06:30:00 GMT",
          "category": "neutral news",
          "confidence": 0.18036486208438873,
          "weight": 0.0,
          "ai_model": "XLM-RoBERTa-Large-XNLI",
          "ai_confidence_score": "18.0%",
          "detected_lang": "en",
          "is_translated": false,
          "country": "Bulgaria"
        },
        {
          "title": "Bulgaria approved €1.5 nillion for road to Zograf Monastery on Mount Athos - Orthodox Times",
          "translated_title": null,
          "link": "https://news.google.com/rss/articles/CBMiowFBVV95cUxQelNOTVZXanJIOFVBT2E4RGptTGEtVDItQTlzYnN2MDBXcksxRGNFZ3NUNF9GUm9RRERCcVlNamhOVmNYTS1LOHhUdk8tc1NUTWtNTUJva0pRTkI1WGRnWmFEQ3VSdlJrX1EzUi05X1BoOEh3MDZmSDZkMGJSZDI2NGgzOXQ3ZElxWEVLUU9mTVlnTzNwRmdTZ3I0dUZ4RHBGOW9F?oc=5",
          "date": "Sat, 07 Feb 2026 15:35:35 GMT",
          "category": "neutral news",
          "confidence": 0.24118079245090485,
          "weight": 0.0,
          "ai_model": "XLM-RoBERTa-Large-XNLI",
          "ai_confidence_score": "24.1%",
          "detected_lang": "local",
          "is_translated": false,
          "country": "Bulgaria"
        },
        {
          "title": "Europe's Oldest Gold: Archeologists found 6,500-year-old gold in Bulgaria revealing ancient metallurgy - Moneycontrol",
          "translated_title": null,
          "link": "https://news.google.com/rss/articles/CBMi8gFBVV95cUxORC1ES0w5WlMzY1BBdGFkaTZEbFhpdVNKZm1BQ0JoYUVyY21heW9jRjdBX3JvZE1fX1lteERxaFppbHZCeDl0ZjlLY0YtUzFYdklwalZiTHBOblRBeElEaTRDOUR6U2lwcjF1cEtFU3N5Z3RMUWNVZEwxeVJEakFZZDQ0MU9kOFByMElxbWpxMnRaZkEtRGlHdzBNVWJQU1VsNXRVeHJQVFhVWHpjcTNJeXZQcVFLNkgwOVJxV3puSHRodGxOb0ZSMmd6ajM3VGdYYTVmclNpLWcydE1ib2ZTNFk1NDFpcHRwYTBxT3RtZzd6Z9IB9wFBVV95cUxQSHVQeFhhOElkcXRnVjYxczlpYmlBT21rVURxSVBKbWcxdnVHWjhUenotZUpfLXdoTFlUOGdHclRuX29LR2RpWUxoa3A1U05YNDl6aVNpTkNnYm10OXlGQXlUTGxOOFlaUzY5THoxNzFzNGJrTThfREJuX3dqZW9pMFFHOUxxTGtQWUExRVZuZWpCYzQyRVkwNlVIZUMwcl9EZWhSREtpX0Zaam5mWlpCQm1UVHVVNXVldk4tcWhZTWhObENHNXJ2SXFlelNHbDR1dy1rM0F5MTVsVEVsd1hRZ2VaY1lhdnRhX0cyLVFZQUdWSU5JREJv?oc=5",
          "date": "Sun, 08 Feb 2026 06:28:11 GMT",
          "category": "violent protest",
          "confidence": 0.32436126470565796,
          "weight": 0.0,
          "ai_model": "XLM-RoBERTa-Large-XNLI",
          "ai_confidence_score": "32.4%",
          "detected_lang": "en",
          "is_translated": false,
          "country": "Bulgaria"
        },
        {
          "title": "Bulgarian amb. in Cairo marks 100 years of Egypt-Bulgaria relations, growing partnership in investment, trade - Egypt Independent",
          "translated_title": null,
          "link": "https://news.google.com/rss/articles/CBMi0gFBVV95cUxPaHR5cUdSX2J5X2YySjB5UlJ5SjdLYS1ja240N09SdjRobHcyRU0zWmNWMzQ5Ul9rYUh3Z0xpclZIYVctRmNpaThtcTlhdWU3Zy1WNlRBdzR1dXRFd0tFSjhUN3oxcGw4dTNYOTJTZVNDcEFXZEN6RmswalVINXNMZS1maldVUTdNaUc4SU1WdGcxTjYyMzJ2WHQ2T0ZlWUJEcEc3eU9SQTU3M1pDY1FHUDJPMWpqbF9BWlhpaV81RmpXU1hMOWF5M2ZDdzhTa0d3UXc?oc=5",
          "date": "Sat, 07 Feb 2026 10:30:40 GMT",
          "category": "violent protest",
          "confidence": 0.38536274433135986,
          "weight": 0.0,
          "ai_model": "XLM-RoBERTa-Large-XNLI",
          "ai_confidence_score": "38.5%",
          "detected_lang": "en",
          "is_translated": false,
          "country": "Bulgaria"
        },
        {
          "title": "Bulgarian National Bank: 81% of Lev Cash Withdrawn as Euro Fully Takes Over - Novinite.com",
          "translated_title": null,
          "link": "https://news.google.com/rss/articles/CBMiuAFBVV95cUxQVU9pcl9qM2Z5a0dkdC1lbjZtNm1KYlYtOHhSaDF6dGh3dVFwSUM4TVdqblhfbUtOY2FyMDFMMXE0bmpDWGlWS2NPVTVlMHhMemFwQjZtUllqTTBoVmR3X0FZX2h6akRkNE0zM2hZeFp4MDE0RjIyc2oyZkIzLTEybVNFNG9DWEZrdThTLVQ4VkZaQ0tTc2hMR01sTW9ya1JRX21nQm04LXhxSW1GaTNhb2p6bU91WlNH?oc=5",
          "date": "Sun, 08 Feb 2026 08:48:45 GMT",
          "category": "economic crisis",
          "confidence": 0.19722729921340942,
          "weight": 0.0,
          "ai_model": "XLM-RoBERTa-Large-XNLI",
          "ai_confidence_score": "19.7%",
          "detected_lang": "en",
          "is_translated": false,
          "country": "Bulgaria"
        },
        {
          "title": "Bulgarian Socialist Party elects Krum Zarkov as its new leader - The Sofia Globe",
          "translated_title": null,
          "link": "https://news.google.com/rss/articles/CBMingFBVV95cUxQTFFLWnRQOEtSZWtMWnUzN0dGX0U0T1pEeTBUbXRWbUdTVDdxRHlIN2tPdkZUNGp0dnRIb3R0UmxlMFBnbnBLdjE4SE9sOFFQeU56bmN5Yk44dTIyUjlMeU9jRS1PUHF0d0RxRU9UVTA3OXQ4dmZpWDlvZEx1cmhQalJFU3JqdDUxQkVoR1ZMcVZiN2UyMUdvZ1VxeG1kUQ?oc=5",
          "date": "Sat, 07 Feb 2026 22:05:59 GMT",
          "category": "violent protest",
          "confidence": 0.20327512919902802,
          "weight": 0.0,
          "ai_model": "XLM-RoBERTa-Large-XNLI",
          "ai_confidence_score": "20.3%",
          "detected_lang": "en",
          "is_translated": false,
          "country": "Bulgaria"
        },
        {
          "title": "Phillgood Festival Launches In Bulgaria, With The Cure, Gorillaz, And Moby - That Eric Alper",
          "translated_title": null,
          "link": "https://news.google.com/rss/articles/CBMiswFBVV95cUxNaGdUUXZJOTBHeUhKU1BrQ0pzLU03Y09MbmNCY0cyMk96bFVDc1FYVWVFa3B5MmhsbHBWSWJWQUU2Y0p6NE9YRFNOSnV3VXVYZXowbEVCZ3Jic2x3TFpxb24yTnllcDE0cDlLREhTak84VGZVTnJBVldMZmFwMXhqWUw2ZW03elU4YzRZMGxoRXcxSnlTcTQtam1TdlB3bHNLNXNjMkZ3VUppX0duTWlsSmZmWQ?oc=5",
          "date": "Fri, 06 Feb 2026 22:33:23 GMT",
          "category": "neutral news",
          "confidence": 0.39462628960609436,
          "weight": 0.0,
          "ai_model": "XLM-RoBERTa-Large-XNLI",
          "ai_confidence_score": "39.5%",
          "detected_lang": "en",
          "is_translated": false,
          "country": "Bulgaria"
        }
      ]
    }
  },
  "history": [
    {
      "timestamp": "2026-02-06T18:05:00.076196",
      "main_index": 7.79,
      "index": 7.79,
      "type": "historical"
    },
    {
      "timestamp": "2026-02-06T19:15:34.213198",
      "main_index": 7.58,
      "index": 7.58,
      "type": "historical"
    },
    {
      "timestamp": "2026-02-06T20:03:51.695488",
      "main_index": 7.31,
      "index": 7.31,
      "type": "historical"
    },
    {
      "timestamp": "2026-02-06T21:02:28.297169",
      "main_index": 7.64,
      "index": 7.64,
      "type": "historical"
    },
    {
      "timestamp": "2026-02-06T21:52:00.465609",
      "main_index": 7.36,
      "index": 7.36,
      "type": "historical"
    },
    {
      "timestamp": "2026-02-06T22:48:43.253872",
      "main_index": 7.52,
      "index": 7.52,
      "type": "historical"
    },
    {
      "timestamp": "2026-02-06T23:53:56.793897",
      "main_index": 7.26,
      "index": 7.26,
      "type": "historical"
    },
    {
      "timestamp": "2026-02-07T02:58:51.821421",
      "main_index": 7.67,
      "index": 7.67,
      "type": "historical"
    },
    {
      "timestamp": "2026-02-07T04:58:01.763365",
      "main_index": 7.6,
      "index": 7.6,
      "type": "historical"
    },
    {
      "timestamp": "2026-02-07T06:03:05.378067",
      "main_index": 7.74,
      "index": 7.74,
      "type": "historical"
    },
    {
      "timestamp": "2026-02-07T07:06:37.405093",
      "main_index": 7.62,
      "index": 7.62,
      "type": "historical"
    },
    {
      "timestamp": "2026-02-07T07:55:29.843878",
      "main_index": 7.74,
      "index": 7.74,
      "type": "historical"
    },
    {
      "timestamp": "2026-02-07T09:01:10.846904",
      "main_index": 7.71,
      "index": 7.71,
      "type": "historical"
    },
    {
      "timestamp": "2026-02-07T09:53:01.182621",
      "main_index": 7.73,
      "index": 7.73,
      "type": "historical"
    },
    {
      "timestamp": "2026-02-07T10:52:37.295968",
      "main_index": 7.8,
      "index": 7.8,
      "type": "historical"
    },
    {
      "timestamp": "2026-02-07T11:41:35.302455",
      "main_index": 8.08,
      "index": 8.08,
      "type": "historical"
    },
    {
      "timestamp": "2026-02-07T13:18:06.597037",
      "main_index": 7.96,
      "index": 7.96,
      "type": "historical"
    },
    {
      "timestamp": "2026-02-07T14:46:30.584393",
      "main_index": 7.83,
      "index": 7.83,
      "type": "historical"
    },
    {
      "timestamp": "2026-02-07T15:45:34.704239",
      "main_index": 7.86,
      "index": 7.86,
      "type": "historical"
    },
    {
      "timestamp": "2026-02-07T16:53:08.859944",
      "main_index": 7.62,
      "index": 7.62,
      "type": "historical"
    },
    {
      "timestamp": "2026-02-07T17:46:04.713099",
      "main_index": 7.62,
      "index": 7.62,
      "type": "historical"
    },
    {
      "timestamp": "2026-02-07T18:58:22.483525",
      "main_index": 7.79,
      "index": 7.79,
      "type": "historical"
    },
    {
      "timestamp": "2026-02-07T19:46:40.827054",
      "main_index": 7.6,
      "index": 7.6,
      "type": "historical"
    },
    {
      "timestamp": "2026-02-07T20:51:30.179052",
      "main_index": 7.77,
      "index": 7.77,
      "type": "historical"
    },
    {
      "timestamp": "2026-02-07T21:55:40.031886",
      "main_index": 8.05,
      "index": 8.05,
      "type": "historical"
    },
    {
      "timestamp": "2026-02-07T22:47:10.979079",
      "main_index": 7.78,
      "index": 7.78,
      "type": "historical"
    },
    {
      "timestamp": "2026-02-07T23:52:02.596148",
      "main_index": 7.74,
      "index": 7.74,
      "type": "historical"
    },
    {
      "timestamp": "2026-02-08T03:33:35.682679",
      "main_index": 7.61,
      "index": 7.61,
      "type": "historical"
    },
    {
      "timestamp": "2026-02-08T05:41:49.607530",
      "main_index": 7.39,
      "index": 7.39,
      "type": "historical"
    },
    {
      "timestamp": "2026-02-08T07:12:42.805886",
      "main_index": 7.54,
      "index": 7.54,
      "type": "historical"
    },
    {
      "timestamp": "2026-02-08T08:04:37.301192",
      "main_index": 7.34,
      "index": 7.34,
      "type": "historical"
    },
    {
      "timestamp": "2026-02-08T08:55:54.752396",
      "main_index": 7.24,
      "index": 7.24,
      "type": "historical"
    },
    {
      "timestamp": "2026-02-08T09:52:05.130629",
      "main_index": 7.23,
      "index": 7.23,
      "type": "historical"
    },
    {
      "timestamp": "2026-02-08T10:51:00.794517",
      "main_index": 7.2,
      "index": 7.2,
      "type": "historical"
    },
    {
      "timestamp": "2026-02-08T11:44:16.679894",
      "main_index": 7.92,
      "index": 7.92,
      "type": "historical"
    },
    {
      "timestamp": "2026-02-08T13:17:09.398506",
      "main_index": 7.3,
      "index": 7.3,
      "type": "historical"
    },
    {
      "timestamp": "2026-02-08T14:50:03.184580",
      "main_index": 7.77,
      "index": 7.77,
      "type": "historical"
    },
    {
      "timestamp": "2026-02-08T15:46:39.408278",
      "main_index": 7.52,
      "index": 7.52,
      "type": "historical"
    },
    {
      "timestamp": "2026-02-08T16:52:43.795496",
      "main_index": 7.5,
      "index": 7.5,
      "type": "historical"
    },
    {
      "timestamp": "2026-02-08T17:54:04.466686",
      "main_index": 6.94,
      "index": 6.94,
      "type": "historical"
    }
  ],
  "forecast": [
    {
      "timestamp": "2026-02-08T18:54:04.466686",
      "index": 7.29,
      "main_index": 7.29,
      "confidence": 0.34,
      "type": "forecast"
    },
    {
      "timestamp": "2026-02-08T19:54:04.466686",
      "index": 7.26,
      "main_index": 7.26,
      "confidence": 0.31,
      "type": "forecast"
    },
    {
      "timestamp": "2026-02-08T20:54:04.466686",
      "index": 7.24,
      "main_index": 7.24,
      "confidence": 0.3,
      "type": "forecast"
    },
    {
      "timestamp": "2026-02-08T21:54:04.466686",
      "index": 7.22,
      "main_index": 7.22,
      "confidence": 0.3,
      "type": "forecast"
    },
    {
      "timestamp": "2026-02-08T22:54:04.466686",
      "index": 7.19,
      "main_index": 7.19,
      "confidence": 0.3,
      "type": "forecast"
    },
    {
      "timestamp": "2026-02-08T23:54:04.466686",
      "index": 7.17,
      "main_index": 7.17,
      "confidence": 0.3,
      "type": "forecast"
    }
  ],
  "methodology": {
    "name": "Modified Goldstein Scale",
    "description": "AI-powered threat classification using XLM-RoBERTa multilingual model with category-weighted scoring",
    "weights": {
      "military conflict": 10.0,
      "terrorist act": 9.0,
      "violent protest": 7.0,
      "political crisis": 6.0,
      "economic crisis": 4.0,
      "humanitarian crisis": 3.0,
      "peaceful diplomacy": -2.0,
      "neutral news": 0.0
    },
    "formula": "ThreatIndex = log10(1 + sum(category_weight * confidence)) * 3.5",
    "scale": {
      "min": 1.0,
      "max": 10.0,
      "thresholds": {
        "STABLE": [
          1.0,
          4.0
        ],
        "ELEVATED": [
          4.0,
          7.0
        ],
        "CRITICAL": [
          7.0,
          10.0
        ]
      }
    }
  }
}